setup.cfg
setup.py
bazaarrecipeinfrae/__init__.py
bazaarrecipeinfrae.egg-info/PKG-INFO
bazaarrecipeinfrae.egg-info/SOURCES.txt
bazaarrecipeinfrae.egg-info/dependency_links.txt
bazaarrecipeinfrae.egg-info/entry_points.txt
bazaarrecipeinfrae.egg-info/not-zip-safe
bazaarrecipeinfrae.egg-info/top_level.txt