Metadata-Version: 1.0
Name: bazaarrecipeinfrae
Version: 0.1.2dev
Summary: Buildout recipe for Bazaar
Home-page: https://launchpad.net/bazaarrecipe
Author: foring.net
Author-email: sviluppo@foring.net
License: GPL
Platform: UNKNOWN
Classifier: Framework :: Buildout
Classifier: Topic :: Software Development :: Build Tools
Classifier: Development Status :: 3 - Alpha
Classifier: License :: OSI Approved :: BSD License
